msgraph_core/__init__.py
msgraph_core/_constants.py
msgraph_core/_enums.py
msgraph_core/base_graph_request_adapter.py
msgraph_core/graph_client_factory.py
msgraph_core/authentication/__init__.py
msgraph_core/authentication/azure_identity_authentication_provider.py
msgraph_core/middleware/__init__.py
msgraph_core/middleware/async_graph_transport.py
msgraph_core/middleware/request_context.py
msgraph_core/middleware/telemetry.py
msgraph_core/middleware/options/__init__.py
msgraph_core/middleware/options/graph_telemetry_handler_option.py
msgraph_core/models/__init__.py
msgraph_core/models/large_file_upload_session.py
msgraph_core/models/page_result.py
msgraph_core/models/upload_result.py
msgraph_core/requests/__init__.py
msgraph_core/requests/batch_request_builder.py
msgraph_core/requests/batch_request_content.py
msgraph_core/requests/batch_request_content_collection.py
msgraph_core/requests/batch_request_item.py
msgraph_core/requests/batch_response_content.py
msgraph_core/requests/batch_response_content_collection.py
msgraph_core/requests/batch_response_item.py
msgraph_core/tasks/__init__.py
msgraph_core/tasks/large_file_upload.py
msgraph_core/tasks/page_iterator.py
msgraph_core-1.3.2.dist-info/LICENSE
msgraph_core-1.3.2.dist-info/METADATA
msgraph_core-1.3.2.dist-info/WHEEL
msgraph_core-1.3.2.dist-info/top_level.txt
msgraph_core-1.3.2.dist-info/RECORD
