Metadata-Version: 2.2
Name: msgraph-core
Version: 1.3.2
Summary: Core component of the Microsoft Graph Python SDK
Author-email: Microsoft <graphtooling+python@microsoft.com>
License: MIT License
Project-URL: homepage, https://github.com/microsoftgraph/msgraph-sdk-python-core#readme
Project-URL: repository, https://github.com/microsoftgraph/msgraph-sdk-python-core
Project-URL: documentation, https://github.com/microsoftgraph/msgraph-sdk-python-core/docs
Keywords: msgraph,openAPI,Microsoft,Graph
Classifier: Development Status :: 5 - Production/Stable
Classifier: Programming Language :: Python :: 3.9
Classifier: Programming Language :: Python :: 3.10
Classifier: Programming Language :: Python :: 3.11
Classifier: Programming Language :: Python :: 3.12
Classifier: Programming Language :: Python :: 3.13
Classifier: License :: OSI Approved :: MIT License
Requires-Python: >=3.9
License-File: LICENSE
Requires-Dist: microsoft-kiota-abstractions<2.0.0,>=1.8.0
Requires-Dist: microsoft-kiota-authentication-azure<2.0.0,>=1.8.0
Requires-Dist: microsoft-kiota-http<2.0.0,>=1.8.0
Requires-Dist: httpx[http2]>=0.23.0
Provides-Extra: dev
Requires-Dist: yapf; extra == "dev"
Requires-Dist: bumpver; extra == "dev"
Requires-Dist: isort; extra == "dev"
Requires-Dist: pylint; extra == "dev"
Requires-Dist: pytest; extra == "dev"
Requires-Dist: mypy; extra == "dev"
